aiorb/__init__.py
aiorb/_version.py
aiorb/exceptions.py
aiorb/utils.py
aiorb/backends/__init__.py
aiorb/backends/sql/__init__.py
aiorb/backends/sql/base.py
aiorb/backends/sql/postgres.py
aiorb/backends/sql/utils.py
aiorb/core/__init__.py
aiorb/core/collection.py
aiorb/core/collector.py
aiorb/core/context.py
aiorb/core/decorators.py
aiorb/core/field.py
aiorb/core/index.py
aiorb/core/model.py
aiorb/core/model_type.py
aiorb/core/query.py
aiorb/core/query_group.py
aiorb/core/reference.py
aiorb/core/schema.py
aiorb/core/store.py
aiorb/core/store_backend.py
aiorb-0.0.dev0.dist-info/DESCRIPTION.rst
aiorb-0.0.dev0.dist-info/METADATA
aiorb-0.0.dev0.dist-info/RECORD
aiorb-0.0.dev0.dist-info/WHEEL
aiorb-0.0.dev0.dist-info/metadata.json
aiorb-0.0.dev0.dist-info/top_level.txt
