Metadata-Version: 2.0
Name: aiorb
Version: 0.0.dev0
Summary: Async Database ORM
Home-page: https://github.com/aiorb/aiorb
Author: eric.hulser@gmail.com
Author-email: eric.hulser@gmail.com
License: MIT
Platform: UNKNOWN
Requires-Dist: aenum
Requires-Dist: dotted
Requires-Dist: inflection
Provides-Extra: dev
Requires-Dist: flake8; extra == 'dev'
Requires-Dist: flake8-docstrings; extra == 'dev'
Requires-Dist: flake8-import-order; extra == 'dev'
Requires-Dist: hacking; extra == 'dev'
Requires-Dist: recommonmark; extra == 'dev'
Requires-Dist: sphinx; extra == 'dev'
Requires-Dist: sphinxcontrib-napoleon; extra == 'dev'
Requires-Dist: sphinx-bootstrap-theme; extra == 'dev'
Provides-Extra: postgres
Requires-Dist: asyncpg; extra == 'postgres'
